py_jwt_cpp-0.1.0.dist-info/RECORD
py_jwt_cpp-0.1.0.dist-info/METADATA
py_jwt_cpp-0.1.0.dist-info/WHEEL
py_jwt_cpp/jwt_cpp.cpython-311-x86_64-linux-gnu.so
py_jwt_cpp/__init__.py
py_jwt_cpp/jwt_wrapper.cpp
py_jwt_cpp.libs/libcom_err-2abe824b.so.2.1
py_jwt_cpp.libs/libgssapi_krb5-497db0c6.so.2.2
py_jwt_cpp.libs/libssl-cd1d6220.so.1.0.2k
py_jwt_cpp.libs/libpcre-9513aab5.so.1.2.0
py_jwt_cpp.libs/libkrb5support-d0bcff84.so.0.1
py_jwt_cpp.libs/libkeyutils-dfe70bd6.so.1.5
py_jwt_cpp.libs/libcrypto-d3570994.so.1.0.2k
py_jwt_cpp.libs/libselinux-0922c95c.so.1
py_jwt_cpp.libs/libk5crypto-b1f99d5c.so.3.1
py_jwt_cpp.libs/libkrb5-fcafa220.so.3.3
