Metadata-Version: 2.1
Name: py_jwt_cpp
Version: 0.1.0
Summary: A Python wrapper around jwt-cpp
Author: Yanghsing Lin
Author-email: yanghsing.lin@gmail.com
Requires-Python: >=3.8
Classifier: Programming Language :: Python :: 3
Classifier: Programming Language :: Python :: 3.8
Classifier: Programming Language :: Python :: 3.9
Classifier: Programming Language :: Python :: 3.10
Classifier: Programming Language :: Python :: 3.11
Classifier: Programming Language :: Python :: 3.12
